nvboard/rtl_prj/p20_fsm/vsrc/com_fsm.v
module com_fsm (
     clk
    ,rst_n
    ,one
    ,half
    ,pi_quit
    ,po_money
    ,po_cola
    ,quit_clk
);
    input      clk, rst_n, one,half,pi_quit;
    output  reg   po_cola,po_money,quit_clk;

    parameter s0 = 3'b000, s1 = 3'b001, s2 = 3'b010, s3 = 3'b011, s4 = 3'b100;
    reg       [2:0]                      state;
    wire      [1:0]                   pi_money;
    assign               pi_money = {one,half};         // 不投币（00） 投half(01) 投one(10)

    //  退钱脉冲  利用寄存器打一拍，将pi_quit电平保持一个时钟周期
    always @(posedge clk or negedge rst_n) begin
        if (!rst_n) begin
            quit_clk <= 1'b0;
        end else begin
            quit_clk <= pi_quit;                // 打一拍  
        end
    end

//第一段状态机，描述当前状态state如何根据输入跳转到下一状态
    always @(posedge clk or negedge rst_n) begin
        if (!rst_n) begin
            state <= s0;
        end else if ((( pi_quit && !quit_clk ) && (state != s0))) begin
            state <= s0;
        end else begin
                case (state)
                    s0 : case (pi_money)                    // 0
                            2'b01  :state <= s1;
                            2'b10  :state <= s2;
                            default:state <= s0;
                         endcase
                    s1 : case (pi_money)                    // 0.5
                            2'b01  :state <= s2;
                            2'b10  :state <= s3;
                            default:state <= s1;
                         endcase     
                    s2 : case (pi_money)                    // 1
                            2'b01  :state <= s3;
                            2'b10  :state <= s4;
                            default:state <= s2;
                         endcase
                    s3 : case (pi_money)                    // 1.5
                            2'b01  :state <= s4;
                            2'b10  :state <= s0;
                            default:state <= s3;
                         endcase                      
                    s4 : case (pi_money)                    // 2
                            2'b01  :state <= s0;
                            2'b10  :state <= s0;
                            default:state <= s4;
                         endcase                      
                    default :state <= s0;
                endcase
            end
    end

//第二段状态机，描述当前状态state和输入pi_money如何影响po_cola输出
    always @(posedge clk or negedge rst_n) begin
        if (!rst_n) begin
            po_cola <=1'b0;
        end else begin
            if(((state == s3) && (pi_money == 2'b10))  || 
               ((state == s4) && (pi_money == 2'b10))  ||
               ((state == s4) && (pi_money == 2'b01)))       begin
                po_cola <= 1'b1;
            end
            else po_cola <= 1'b0;
        end
    end

//第三段状态机，描述当前状态state和输入pi_money如何影响po_money输出
    always @(posedge clk or negedge rst_n) begin
        if (!rst_n) begin
            po_money <= 1'b0;
        end else begin
            if (((pi_quit && !quit_clk)  && (state != s0))) begin
                po_money <= 1'b1;
            end else if((state == s4) && (pi_money == 2'b10)) begin
                po_money <= 1'b1;
            end else 
                po_money <= 1'b0;
        end 
    end
endmodule

/*
通过pi_qiut和quit_clk在同一时钟周期内，上升沿采样时
"在当前周期同步电路内的上升沿来临时属于quit_clk的上升沿"
更精确的说法是：我们检测到的是"在时钟采样时刻，信号从0变为1"

*/

nvboard/rtl_prj/p20_fsm/vsrc/fsm.v
module fsm (
     clk
    ,rst_n
    ,din
    ,dout
);
    input           clk,rst_n,din;
    output   reg             dout;

    parameter s0 = 4'b0000, s1 = 4'b0001, s2 = 4'b0010, s3 = 4'b0011;
    parameter s4 = 4'b0100, s5 = 4'b0101, s6 = 4'b0110, s7 = 4'b0111, s8 = 4'b1000;
    reg     [3:0]           state;

    //第一段状态机，描述当前状态state如何根据输入跳转到下一状态
    always @(posedge clk  or negedge rst_n) begin
        if (!rst_n) begin
            state <= s0;
        end else begin
            case (state)
                s0 : state <= (din == 1'b0) ? s1 : s5;
                s1 : state <= (din == 1'b0) ? s2 : s5;
                s2 : state <= (din == 1'b0) ? s3 : s5;
                s3 : state <= (din == 1'b0) ? s4 : s5;
                s4 : state <= (din == 1'b0) ? s4 : s5;
                s5 : state <= (din == 1'b1) ? s6 : s1;
                s6 : state <= (din == 1'b1) ? s7 : s1;
                s7 : state <= (din == 1'b1) ? s8 : s1;              
                s8 : state <= (din == 1'b1) ? s8 : s1;
                default : state <= s0;
            endcase
        end
    end

    //第二段状态机，描述当前状态state和输入pi_money如何影响po_cola输出
    
    always @(posedge clk or negedge rst_n) begin
        if (!rst_n) begin
            dout <= 1'b0;
        end else 
            dout <= ((state == s4) || (state == s8));       // 逻辑或，两者之一任意成立结果都为1  并且dout延迟一拍输出
    end
endmodule

/*
状态机核心：
    1：状态转移图确定每一种状态如何产生
    2：输出结果0/1状态在何时产生？ 在什么状态下产生输出1状态，其余都为0状态
*/

nvboard/rtl_prj/p20_fsm/vsrc/top.v
module top (
     clk
    ,rst_n
    ,one
    ,half
    ,pi_quit
    ,po_money
    ,po_cola
    ,quit_clk
    ,dout
);
    input            clk,rst_n,one,half,pi_quit;
    output       quit_clk,po_money,po_cola,dout;

fsm u_fsm (
     .clk            (clk     )
    ,.rst_n          (rst_n   )
    ,.din            (half    )
    ,.dout           (dout    )
);

com_fsm u_com_fsm (
     .clk            (clk     )
    ,.rst_n          (rst_n   )
    ,.one            (one     )
    ,.half           (half    )
    ,.pi_quit        (pi_quit )
    ,.po_money       (po_money)
    ,.po_cola        (po_cola )
    ,.quit_clk       (quit_clk)
);

endmodule

nvboard/rtl_prj/p20_fsm/sim_obj/top.vcd
$version Generated by VerilatedVcd $end
$timescale 1ps $end
 $scope module TOP $end
  $var wire 1 # clk $end
  $var wire 1 $ rst_n $end
  $var wire 1 % one $end
  $var wire 1 & half $end
  $var wire 1 ' pi_quit $end
  $var wire 1 ( quit_clk $end
  $var wire 1 ) po_money $end
  $var wire 1 * po_cola $end
  $var wire 1 + dout $end
  $scope module top $end
   $var wire 1 # clk $end
   $var wire 1 $ rst_n $end
   $var wire 1 % one $end
   $var wire 1 & half $end
   $var wire 1 ' pi_quit $end
   $var wire 1 ( quit_clk $end
   $var wire 1 ) po_money $end
   $var wire 1 * po_cola $end
   $var wire 1 + dout $end
   $scope module u_com_fsm $end
    $var wire 1 # clk $end
    $var wire 1 $ rst_n $end
    $var wire 1 % one $end
    $var wire 1 & half $end
    $var wire 1 ' pi_quit $end
    $var wire 1 * po_cola $end
    $var wire 1 ) po_money $end
    $var wire 1 ( quit_clk $end
    $var wire 3 / s0 [2:0] $end
    $var wire 3 0 s1 [2:0] $end
    $var wire 3 1 s2 [2:0] $end
    $var wire 3 2 s3 [2:0] $end
    $var wire 3 3 s4 [2:0] $end
    $var wire 3 , state [2:0] $end
    $var wire 2 - pi_money [1:0] $end
   $upscope $end
   $scope module u_fsm $end
    $var wire 1 # clk $end
    $var wire 1 $ rst_n $end
    $var wire 1 & din $end
    $var wire 1 + dout $end
    $var wire 4 4 s0 [3:0] $end
    $var wire 4 5 s1 [3:0] $end
    $var wire 4 6 s2 [3:0] $end
    $var wire 4 7 s3 [3:0] $end
    $var wire 4 8 s4 [3:0] $end
    $var wire 4 9 s5 [3:0] $end
    $var wire 4 : s6 [3:0] $end
    $var wire 4 ; s7 [3:0] $end
    $var wire 4 < s8 [3:0] $end
    $var wire 4 . state [3:0] $end
   $upscope $end
  $upscope $end
 $upscope $end
$enddefinitions $end


#0
0#
1$
0%
0&
0'
0(
0)
0*
0+
b000 ,
b00 -
b0000 .
b000 /
b001 0
b010 1
b011 2
b100 3
b0000 4
b0001 5
b0010 6
b0011 7
b0100 8
b0101 9
b0110 :
b0111 ;
b1000 <
#5
1#
b0001 .
#10
0#
0$
1%
1'
b10 -
b0000 .
#15
1#
#20
0#
#25
1#
#30
0#
1$
0%
0'
b00 -
#35
1#
b0001 .
#40
0#
1%
b10 -
#45
1#
b010 ,
b0010 .
#50
0#
0%
1&
b01 -
#55
1#
b011 ,
b0101 .
#60
0#
#65
1#
b100 ,
b0110 .
#70
0#
#75
1#
1*
b000 ,
b0111 .
#80
0#
0&
b00 -
#85
1#
0*
b0001 .
#90
0#
1&
b01 -
#95
1#
b001 ,
b0101 .
#100
0#
1%
0&
b10 -
#105
1#
b011 ,
b0001 .
#110
0#
0%
1'
b00 -
#115
1#
1(
1)
b000 ,
b0010 .
#120
0#
0'
#125
1#
0(
0)
b0011 .
#130
0#
1%
b10 -
#135
1#
b010 ,
b0100 .
#140
0#
0%
1&
b01 -
#145
1#
1+
b011 ,
b0101 .
#150
0#
#155
1#
0+
b100 ,
b0110 .
#160
0#
1%
0&
b10 -
#165
1#
1)
1*
b000 ,
b0001 .
#170
0#
0%
b00 -
#175
1#
0)
0*
b0010 .
#180
0#
1&
b01 -
#185
1#
b001 ,
b0101 .
#190
0#
#195
1#
b010 ,
b0110 .
#200
0#
#205
1#
b011 ,
b0111 .
#210
0#
#215
1#
b100 ,
b1000 .
#220
0#
#225
1#
1*
1+
b000 ,
#230
0#
1%
0&
b10 -
#235
1#
0*
b010 ,
b0001 .
#240
0#
0%
1&
b01 -
#245
1#
0+
b011 ,
b0101 .
#250
0#
0&
b00 -
#255
1#
b0001 .
#260
0#
#265
1#
b0010 .
#270
0#
#275
1#
b0011 .
#280
0#
#285
1#
b0100 .
#290
0#
#295
1#
1+
#300
0#
1&
b01 -
#305
1#
b100 ,
b0101 .
#310
0#
#315
1#
1*
0+
b000 ,
b0110 .
#320
0#
1%
0&
b10 -
#325
1#
0*
b010 ,
b0001 .
#330
0#
0%
1&
b01 -
#335
1#
b011 ,
b0101 .
#340
0#
0&
b00 -
#345
1#
b0001 .
#350
0#
#355
1#
b0010 .
#360
0#
#365
1#
b0011 .
#370
0#
#375
1#
b0100 .
#380
0#
#385
1#
1+
